napari_annotate/__init__.py
napari_annotate/_annotate.py
napari_annotate/_version.py
napari_annotate/napari.yaml
napari_annotate-0.0.2.dist-info/LICENSE.txt
napari_annotate-0.0.2.dist-info/METADATA
napari_annotate-0.0.2.dist-info/WHEEL
napari_annotate-0.0.2.dist-info/entry_points.txt
napari_annotate-0.0.2.dist-info/top_level.txt
napari_annotate-0.0.2.dist-info/RECORD
