Metadata-Version: 2.1
Name: napari-annotate
Version: 0.0.2
Summary: Annotate large 2D slides
Home-page: https://github.com/WyssCenter
Author: Jules Scholler
Author-email: jules.scholler@wysscenter.ch
License: MPL-2.0
Classifier: Development Status :: 2 - Pre-Alpha
Classifier: Intended Audience :: Developers
Classifier: Framework :: napari
Classifier: Topic :: Software Development :: Testing
Classifier: Programming Language :: Python
Classifier: Programming Language :: Python :: 3
Classifier: Programming Language :: Python :: 3.7
Classifier: Programming Language :: Python :: 3.8
Classifier: Programming Language :: Python :: 3.9
Classifier: Operating System :: OS Independent
Classifier: License :: OSI Approved :: Mozilla Public License 2.0 (MPL 2.0)
Requires-Python: >=3.8
License-File: LICENSE.txt
Requires-Dist: numpy
Requires-Dist: napari[all]
Requires-Dist: napari-tools-menu
Requires-Dist: magic-class
Requires-Dist: napari-plugin-engine (>=0.1.4)
